juduino.py
juduino-1.0.0b1.dist-info/METADATA
juduino-1.0.0b1.dist-info/WHEEL
juduino-1.0.0b1.dist-info/top_level.txt
juduino-1.0.0b1.dist-info/RECORD
